README.md
setup.py
async_pluct/__init__.py
async_pluct/http.py
async_pluct/resource.py
async_pluct/schema.py
async_pluct/session.py
async_pluct.egg-info/PKG-INFO
async_pluct.egg-info/SOURCES.txt
async_pluct.egg-info/dependency_links.txt
async_pluct.egg-info/requires.txt
async_pluct.egg-info/top_level.txt