Metadata-Version: 1.1
Name: async-pluct
Version: 0.3.4
Summary: JSON Hyper Schema client
Home-page: https://github.com/globocom/async-pluct
Author: Lucas Stephanou
Author-email: domluc@gmail.com
License: UNKNOWN
Platform: UNKNOWN
Classifier: Development Status :: 4 - Beta
Classifier: Environment :: No Input/Output (Daemon)
Classifier: Intended Audience :: Developers
Classifier: License :: OSI Approved :: MIT License
Classifier: Operating System :: Unix
Classifier: Programming Language :: Python :: 2.7
Classifier: Programming Language :: Python :: 3.6
